[
  { "id": 1, "title": "Suit (2-piece)", "price": "31" },
  { "id": 2, "title": "Suit (3-piece)", "price": "41" },
  { "id": 3, "title": "African Agbada", "price": "26" },
  { "id": 4, "title": "African Dress", "price": "31" },
  { "id": 5, "title": "African Female Dress (2-piece)", "price": "36" },
  { "id": 6, "title": "African Shirt + Pant + Agbada (3-piece)", "price": "53" },
  { "id": 7, "title": "African Shirt and Pant (2-piece)", "price": "31" },
  { "id": 8, "title": "Bag", "price": "31" },
  { "id": 9, "title": "Blouse", "price": "10" },
  { "id": 10, "title": "Blouse (Long)", "price": "13" },
  { "id": 11, "title": "Body Suit", "price": "8" },
  { "id": 12, "title": "Choir Robe", "price": "29" },
  { "id": 13, "title": "Choir Robe (Pleated)", "price": "36" },
  { "id": 14, "title": "Dress", "price": "26" },
  { "id": 15, "title": "Dress (Long)", "price": "36" },
  { "id": 16, "title": "Dress (Evening)", "price": "41" },
  { "id": 17, "title": "Dress (Pleated)", "price": "51" },
  { "id": 18, "title": "Dress + Jacket", "price": "31" },
  { "id": 19, "title": "Dress + Scarf", "price": "28" },
  { "id": 20, "title": "Fur Coat", "price": "61" },
  { "id": 21, "title": "Graduation Robe", "price": "31" },
  { "id": 22, "title": "Hat", "price": "16" },
  { "id": 23, "title": "Headwarmer/Face Item (Small)", "price": "14" },
  { "id": 24, "title": "Hoodie", "price": "19" },
  { "id": 25, "title": "Household - Small", "price": "21" },
  { "id": 26, "title": "Jacket", "price": "21" },
  { "id": 27, "title": "Jeans", "price": "16" },
  { "id": 28, "title": "Joggers", "price": "14" },
  { "id": 29, "title": "Jumpsuit", "price": "23" },
  { "id": 30, "title": "Overcoat (Waist Length)", "price": "36" },
  { "id": 31, "title": "Overcoat (Long)", "price": "46" },
  { "id": 32, "title": "Pant + Jacket", "price": "31" },
  { "id": 33, "title": "Parka", "price": "41" },
  { "id": 34, "title": "Parka - Canada Goose", "price": "61" },
  { "id": 35, "title": "Parka - Long", "price": "51" },
  { "id": 36, "title": "Polo Shirt", "price": "10" },
  { "id": 37, "title": "Raincoat", "price": "36" },
  { "id": 38, "title": "Rug", "price": "50" },
  { "id": 39, "title": "Saree", "price": "31" },
  { "id": 40, "title": "Saree (Top and Bottom)", "price": "41" },
  { "id": 41, "title": "Scarf", "price": "16" },
  { "id": 42, "title": "Shirt", "price": "8" },
  { "id": 43, "title": "Shoe", "price": "31" },
  { "id": 44, "title": "Shorts", "price": "13" },
  { "id": 45, "title": "Silk Blouse", "price": "16" },
  { "id": 46, "title": "Silk Pants", "price": "21" },
  { "id": 47, "title": "Silk Shirts", "price": "16" },
  { "id": 48, "title": "Skirt", "price": "14" },
  { "id": 49, "title": "Skirt (Pleated)", "price": "20" },
  { "id": 50, "title": "Sleeping Bag", "price": "41" },
  { "id": 51, "title": "Sport Coat", "price": "23" },
  { "id": 52, "title": "Sport Shirt", "price": "8" },
  { "id": 53, "title": "Spring Jacket", "price": "29" },
  { "id": 54, "title": "Sweat Pants", "price": "16" },
  { "id": 55, "title": "Sweat Shirt", "price": "16" },
  { "id": 56, "title": "Sweater (Long)", "price": "19" },
  { "id": 57, "title": "Sweater (Short)", "price": "16" },
  { "id": 58, "title": "Sweater Jacket", "price": "21" },
  { "id": 59, "title": "Sweatsuit - Hoodie and Pant (2-piece)", "price": "29" },
  { "id": 60, "title": "Table Cloth (Medium)", "price": "31" },
  { "id": 61, "title": "Table Cloth (Large)", "price": "51" },
  { "id": 62, "title": "Teddy Bear (32 inches and Lower)", "price": "31" },
  { "id": 63, "title": "Teddy Bear (50 inches and Lower)", "price": "51" },
  { "id": 64, "title": "Teddy Bear (51 inches and Larger)", "price": "71" },
  { "id": 65, "title": "Tie", "price": "12" },
  { "id": 66, "title": "Trousers/Pant", "price": "14" },
  { "id": 67, "title": "Vest", "price": "14" },
  { "id": 68, "title": "Vest (Down/Puff)", "price": "36" },
  { "id": 69, "title": "Waistcoat", "price": "13" },
  { "id": 70, "title": "Wedding Dress", "price": "201" },
  { "id": 71, "title": "Wedding Vail (Small)", "price": "16" },
  { "id": 72, "title": "Wedding Vail (Medium)", "price": "21" },
  { "id": 73, "title": "Wedding Vail (Large)", "price": "31" }
]
